teraboxdl/__init__.py
teraboxdl/config.py
teraboxdl/downloader.py
teraboxdl/exceptions.py
teraboxdl/utils.py
teraboxdl-0.2.dist-info/LICENSE
teraboxdl-0.2.dist-info/METADATA
teraboxdl-0.2.dist-info/WHEEL
teraboxdl-0.2.dist-info/top_level.txt
teraboxdl-0.2.dist-info/RECORD
