Metadata-Version: 2.1
Name: teraboxdl
Version: 0.2
Summary: A package for downloading from Terabox
Home-page: https://github.com/TG-BOTSNETWORK/teraboxdl
Author: Santhosh
Author-email: telegramsanthu@gmail.com
Classifier: Programming Language :: Python :: 3
Classifier: License :: OSI Approved :: MIT License
Classifier: Operating System :: OS Independent
Requires-Python: >=3.6
License-File: LICENSE
Requires-Dist: requests
